searcher/__init__.py
searcher/main.py
searcher/version.py
searcher/enums/Code.py
searcher/enums/Duplicate.py
searcher/models/ITechnialVision.py
searcher/models/Omron.py
searcher/models/SPTVision.py
searcher/models/__init__.py
duples_searcher-0.1.0.dist-info/LICENSE
duples_searcher-0.1.0.dist-info/METADATA
duples_searcher-0.1.0.dist-info/WHEEL
duples_searcher-0.1.0.dist-info/entry_points.txt
duples_searcher-0.1.0.dist-info/top_level.txt
duples_searcher-0.1.0.dist-info/RECORD
