Metadata-Version: 2.1
Name: duples-searcher
Version: 0.1.0
Summary: Search information about duplicates in files
Home-page: https://github.com/MBHuman/duples_searcher
Download-URL: https://github.com/MBHuman/duples_searcher/archive/refs/tags/0.1.0.tar.gz
Author: Evgeny Dmitriev
Author-email: zenka712@mail.ru
License: MIT
Classifier: Programming Language :: Python :: 3
License-File: LICENSE
Requires-Dist: pydantic (==1.10.2)
